MANIFEST.in
setup.cfg
setup.py
cfscraper/__init__.py
cfscraper/exceptions.py
cfscraper/help.py
cfscraper.egg-info/PKG-INFO
cfscraper.egg-info/SOURCES.txt
cfscraper.egg-info/dependency_links.txt
cfscraper.egg-info/requires.txt
cfscraper.egg-info/top_level.txt
cfscraper/interpreters/__init__.py
cfscraper/interpreters/chakracore.py
cfscraper/interpreters/encapsulated.py
cfscraper/interpreters/js2py.py
cfscraper/interpreters/jsunfuck.py
cfscraper/interpreters/native.py
cfscraper/interpreters/nodejs.py
cfscraper/interpreters/v8.py
cfscraper/reCaptcha/2captcha.py
cfscraper/reCaptcha/9kw.py
cfscraper/reCaptcha/__init__.py
cfscraper/reCaptcha/anticaptcha.py
cfscraper/reCaptcha/deathbycaptcha.py
cfscraper/user_agent/__init__.py
cfscraper/user_agent/browsers.json