Metadata-Version: 1.0
Name: cfscraper
Version: 0.17
Summary: A Python module to bypass Cloudflare's anti-bot page.
Home-page: UNKNOWN
Author: UNKNOWN
Author-email: UNKNOWN
License: UNKNOWN
Platform: UNKNOWN
